warriorrest/__init__.py
warriorrest/Actions/__init__.py
warriorrest/Actions/RestActions/__init__.py
warriorrest/Actions/RestActions/rest_actions.py
warriorrest/ClassUtils/__init__.py
warriorrest/ClassUtils/rest_utils_class.py
warriorrest/ProductDrivers/__init__.py
warriorrest/ProductDrivers/rest_driver.py
warriorrest/Utils/__init__.py
warriorrest/Utils/rest_Utils.py
warriorrest-1.0.0.dist-info/METADATA
warriorrest-1.0.0.dist-info/WHEEL
warriorrest-1.0.0.dist-info/top_level.txt
warriorrest-1.0.0.dist-info/RECORD
